whereami/main.py
whereami_mcp-0.1.0.dist-info/licenses/LICENSE
whereami_mcp-0.1.0.dist-info/METADATA
whereami_mcp-0.1.0.dist-info/WHEEL
whereami_mcp-0.1.0.dist-info/entry_points.txt
whereami_mcp-0.1.0.dist-info/top_level.txt
whereami_mcp-0.1.0.dist-info/RECORD
